COPYING
MANIFEST.in
README.rst
setup.py
squadtradefed.egg-info/PKG-INFO
squadtradefed.egg-info/SOURCES.txt
squadtradefed.egg-info/dependency_links.txt
squadtradefed.egg-info/entry_points.txt
squadtradefed.egg-info/requires.txt
squadtradefed.egg-info/top_level.txt
tradefed/__init__.py