Metadata-Version: 1.0
Name: squadtradefed
Version: 1.0
Summary: SQUAD plugin that parses CTS/VTS results
Home-page: https://example.com/examplepluginpackage
Author: Milosz Wasilewski
Author-email: milosz.wasilewski@linaro.org
License: AGPLv3+
Platform: any
